snowflake_ai/__init__.py
snowflake_ai/apps/__init__.py
snowflake_ai/apps/app_page.py
snowflake_ai/apps/base_app.py
snowflake_ai/apps/console_app.py
snowflake_ai/apps/notebook_app.py
snowflake_ai/apps/streamlit_app.py
snowflake_ai/apps/tab_registry.py
snowflake_ai/common/__init__.py
snowflake_ai/common/app_config.py
snowflake_ai/common/app_connect.py
snowflake_ai/common/config_manager.py
snowflake_ai/common/data_connect.py
snowflake_ai/common/oauth_connect.py
snowflake_ai/conf/__init__.py
snowflake_ai/conf/app_config.toml
snowflake_ai/connect/__init__.py
snowflake_ai/connect/authcode_connect.py
snowflake_ai/connect/clientcreds_connect.py
snowflake_ai/connect/connect_manager.py
snowflake_ai/connect/dataframe_factory.py
snowflake_ai/connect/devicecode_connect.py
snowflake_ai/connect/file_connect.py
snowflake_ai/connect/snow_connect.py
snowflake_ai/mlops/__init__.py
snowflake_ai/mlops/flow_context.py
snowflake_ai/mlops/flow_ops.py
snowflake_ai/mlops/flow_pipeline.py
snowflake_ai/mlops/flow_test.py
snowflake_ai/mlops/model_dev.py
snowflake_ai/mlops/model_serve.py
snowflake_ai/mlops/snow_registry.py
snowflake_ai/snowpandas/__init__.py
snowflake_ai/snowpandas/data_prep.py
snowflake_ai/snowpandas/data_setup.py
snowflake_ai/snowpandas/setup_manager.py
snowflake_ai/snowpandas/snow_encoder.py
snowflake_ai/snowpandas/snow_prep.py
snowflake_ai/snowpandas/snow_setup.py
snowflake_ai/snowpandas/snow_transform.py
snowflake_ai-0.5.3.dist-info/LICENSE.txt
snowflake_ai-0.5.3.dist-info/METADATA
snowflake_ai-0.5.3.dist-info/WHEEL
snowflake_ai-0.5.3.dist-info/RECORD
