Metadata-Version: 2.1
Name: snowflake-ai
Version: 0.5.3
Summary: A Snowflake centic Enterprise AI/ML framework with tight integration of popular data science libraries
Home-page: https://github.com/illuminairy-ai/snowflake-ai#readme
License: Apache Software License 2
Keywords: Snowflake,Enterprise,AI/ML,AI,ML,Machine Learning,Illuminairy
Author: Illuminairy AI
Author-email: tony.liu@yahoo.com
Requires-Python: >=3.8, !=2.7.*, !=3.0.*, !=3.1.*, !=3.2.*, !=3.3.*, !=3.4.*, !=3.5.*, !=3.6.*, !=3.7.*, !=3.11.*
Classifier: License :: OSI Approved :: Apache Software License
Classifier: License :: Other/Proprietary License
Classifier: Programming Language :: Python :: 3
Classifier: Programming Language :: Python :: 3.9
Classifier: Programming Language :: Python :: 3.10
Classifier: Programming Language :: Python :: 3.8
Classifier: Topic :: Scientific/Engineering :: Artificial Intelligence
Classifier: Topic :: Software Development :: Libraries :: Python Modules
Requires-Dist: altair (>=4.0.0,<4.1.0)
Requires-Dist: cryptography (>=40.0.2,<42)
Requires-Dist: importlib-resources (>=5.2.0,<=5.12.0)
Requires-Dist: mpmath (>=1.2.1,<1.3.0)
Requires-Dist: pandas (>=1.5.3,<1.6.0)
Requires-Dist: psutil (>=5.9.0,<5.10.0)
Requires-Dist: pyjwt (>=2.7.0,<2.8.0)
Requires-Dist: requests (>=2.28.1,<=2.31.0)
Requires-Dist: scikit-learn (>=1.2.2,<1.3.0)
Requires-Dist: snowflake-connector-python[pandas] (>=3.1.0)
Requires-Dist: snowflake-snowpark-python (>=1.5.0)
Requires-Dist: streamlit (>=1.18.0,<1.19.0)
Requires-Dist: toml (>=0.10.2,<0.11.0)
Requires-Dist: urllib3 (>=1.26.15,<1.27.0)
